{
  "ok": true,
  "tileId": "sauna-control",
  "fetchedAt": "2026-06-26T14:28:00Z",
  "content": {
    "status": "Heating",
    "value": "178F",
    "subtitle": "Target 190F - 22 min remaining - Door closed",
    "metrics": [
      {
        "label": "Target",
        "value": "190F"
      },
      {
        "label": "Duration",
        "value": "22 min"
      }
    ]
  },
  "actions": [
    {
      "id": "start",
      "label": "Start",
      "method": "POST",
      "confirmationText": "Start the sauna with these settings?",
      "fields": [
        {
          "id": "targetTemperature",
          "label": "Target Temperature (F)",
          "type": "number",
          "defaultValue": 190,
          "min": 100,
          "max": 240,
          "step": 1,
          "unit": "°F",
          "required": true
        },
        {
          "id": "duration",
          "label": "Duration (minutes)",
          "type": "number",
          "defaultValue": 180,
          "min": 15,
          "max": 720,
          "step": 15,
          "unit": "minutes",
          "required": true
        }
      ]
    },
    {
      "id": "stop",
      "label": "Stop",
      "method": "POST",
      "confirmationText": "Stop the sauna now?",
      "fields": []
    }
  ]
}
